kappamin.py
kappamin-0.3.1.dist-info/LICENSE
kappamin-0.3.1.dist-info/METADATA
kappamin-0.3.1.dist-info/WHEEL
kappamin-0.3.1.dist-info/top_level.txt
kappamin-0.3.1.dist-info/RECORD
