Metadata-Version: 2.1
Name: kappamin
Version: 0.3.1
Summary: A python3 code for calculations of the minimum limit to thermal conductivity
Home-page: https://github.com/JianboHIT/kappamin
Author: Jianbo ZHU
License: Apache-2.0 license
Keywords: thermal-conductivity,limitation,condensed-matter-physics,phonon-transport
Classifier: Development Status :: 3 - Alpha
Classifier: Programming Language :: Python :: 3
Classifier: Programming Language :: Python :: 3.6
Classifier: Programming Language :: Python :: 3.8
Classifier: Topic :: Scientific/Engineering
Classifier: Topic :: Scientific/Engineering :: Chemistry
Classifier: Topic :: Scientific/Engineering :: Physics
Classifier: Intended Audience :: Science/Research
Classifier: License :: OSI Approved :: Apache Software License
License-File: LICENSE
Requires-Dist: numpy
Requires-Dist: scipy
